setup.py
crc_nd/__init__.py
crc_nd.utils.egg-info/PKG-INFO
crc_nd.utils.egg-info/SOURCES.txt
crc_nd.utils.egg-info/dependency_links.txt
crc_nd.utils.egg-info/namespace_packages.txt
crc_nd.utils.egg-info/requires.txt
crc_nd.utils.egg-info/top_level.txt
crc_nd/utils/__init__.py
crc_nd/utils/django.py
crc_nd/utils/error_mixins.py
crc_nd/utils/errors.py
crc_nd/utils/file_io.py
crc_nd/utils/test_io.py