Metadata-Version: 1.1
Name: crc-nd.utils
Version: 0.2.0
Summary: Utility code for Python projects
Home-page: https://github.com/crc-nd/py-utils
Author: Center for Research Computing, University of Notre Dame
Author-email: crc-ci-developers@listserv.nd.edu
License: UNKNOWN
Platform: UNKNOWN
Classifier: Development Status :: 4 - Beta
Classifier: License :: OSI Approved :: Mozilla Public License 2.0 (MPL 2.0)
Classifier: Intended Audience :: Developers
Classifier: Operating System :: OS Independent
Classifier: Programming Language :: Python :: 2
Classifier: Topic :: Software Development :: Libraries :: Python Modules
Provides: crc_nd.utils
